fild_api_hub-0.0.8.dist-info/licenses/LICENSE
fildapi/__init__.py
fildapi/caller.py
fildapi/method.py
fildapi/schema.py
fildapi/mock/__init__.py
fildapi/mock/data.py
fildapi/mock/service.py
fild_api_hub-0.0.8.dist-info/METADATA
fild_api_hub-0.0.8.dist-info/WHEEL
fild_api_hub-0.0.8.dist-info/top_level.txt
fild_api_hub-0.0.8.dist-info/RECORD
