Metadata-Version: 2.4
Name: fild-api-hub
Version: 0.0.8
Summary: Library to operate api with help of fild contracts
Home-page: https://github.com/elenakulgavaya/fild-api-hub
Author: Elena Kulgavaya
Author-email: elena.kulgavaya@gmail.com
Project-URL: Bug Tracker, https://github.com/elenakulgavaya/fild-api-hub/issues
Classifier: Programming Language :: Python :: 3
Classifier: License :: OSI Approved :: MIT License
Classifier: Operating System :: OS Independent
Requires-Python: >=3.9
License-File: LICENSE
Requires-Dist: deepdiff>=6.5.1
Requires-Dist: fild>=0.1.0
Requires-Dist: fild-cfg>=0.0.1
Requires-Dist: fild-compare>=0.0.3
Requires-Dist: requests
Requires-Dist: pyyaml
Requires-Dist: waiting
Dynamic: license-file
